{"paths":{"0":["Role3X_tex",2],"1":["Role3X_tex",1],"2":["Role3X_ske",0],"3":["Role3X_tex",3,1],"4":["hero3",4]},"types":["dragonBones.DragonBonesAsset","dragonBones.DragonBonesAtlasAsset","cc.Texture2D","cc.SpriteFrame","cc.Prefab"],"uuids":["55Irvr/ldCxa4gJCCI5Gva","41s7t0v4FJA6+Ul3rr8zHQ","733LHvmPVPo4sTpqWyY2+d","97N64L4P9HianHFs9nrzgI","ebrQTZIX1NYK4QwXPuwm+d","ecpdLyjvZBwrvm+cedCcQy"],"scenes":{},"redirect":[5,0],"deps":["internal"],"packs":{"0f1791fe3":[2,4]},"name":"hero3","importBase":"import","nativeBase":"native","debug":false,"isZip":false,"encrypted":false,"versions":{"import":["0f1791fe3","bceea",1,"9e178",0,"7871f",3,"cf6be"],"native":[0,"10889"]}}